odoo10_addon_l10n_it_website_sale_fatturapa-10.0.1.0.0.99.dev4-py3.8-nspkg.pth
odoo/addons/l10n_it_website_sale_fatturapa/README.rst
odoo/addons/l10n_it_website_sale_fatturapa/__init__.py
odoo/addons/l10n_it_website_sale_fatturapa/__manifest__.py
odoo/addons/l10n_it_website_sale_fatturapa/controllers/__init__.py
odoo/addons/l10n_it_website_sale_fatturapa/controllers/main.py
odoo/addons/l10n_it_website_sale_fatturapa/i18n/it.po
odoo/addons/l10n_it_website_sale_fatturapa/i18n/l10n_it_website_sale_fatturapa.pot
odoo/addons/l10n_it_website_sale_fatturapa/readme/DESCRIPTION.rst
odoo/addons/l10n_it_website_sale_fatturapa/static/description/icon.png
odoo/addons/l10n_it_website_sale_fatturapa/static/description/index.html
odoo/addons/l10n_it_website_sale_fatturapa/static/src/js/l10n_it_website_sale_fatturapa.js
odoo/addons/l10n_it_website_sale_fatturapa/views/templates.xml
odoo10_addon_l10n_it_website_sale_fatturapa-10.0.1.0.0.99.dev4.dist-info/METADATA
odoo10_addon_l10n_it_website_sale_fatturapa-10.0.1.0.0.99.dev4.dist-info/WHEEL
odoo10_addon_l10n_it_website_sale_fatturapa-10.0.1.0.0.99.dev4.dist-info/namespace_packages.txt
odoo10_addon_l10n_it_website_sale_fatturapa-10.0.1.0.0.99.dev4.dist-info/top_level.txt
odoo10_addon_l10n_it_website_sale_fatturapa-10.0.1.0.0.99.dev4.dist-info/RECORD
